dependency_injector/__init__.py
dependency_injector/_cwiring.c
dependency_injector/_cwiring.cpython-39-x86_64-linux-gnu.so
dependency_injector/_cwiring.pyi
dependency_injector/_cwiring.pyx
dependency_injector/containers.c
dependency_injector/containers.cpython-39-x86_64-linux-gnu.so
dependency_injector/containers.pxd
dependency_injector/containers.pyi
dependency_injector/containers.pyx
dependency_injector/errors.py
dependency_injector/providers.c
dependency_injector/providers.cpython-39-x86_64-linux-gnu.so
dependency_injector/providers.pxd
dependency_injector/providers.pyi
dependency_injector/providers.pyx
dependency_injector/py.typed
dependency_injector/resources.py
dependency_injector/schema.py
dependency_injector/wiring.py
dependency_injector/ext/__init__.py
dependency_injector/ext/__init__.pyi
dependency_injector/ext/aiohttp.py
dependency_injector/ext/aiohttp.pyi
dependency_injector/ext/flask.py
dependency_injector/ext/flask.pyi
dependency_injector/ext/starlette.py
dependency_injector-4.48.3.dist-info/METADATA
dependency_injector-4.48.3.dist-info/WHEEL
dependency_injector-4.48.3.dist-info/top_level.txt
dependency_injector-4.48.3.dist-info/RECORD
dependency_injector-4.48.3.dist-info/licenses/LICENSE.rst
